mips32_pipe.v
module mips32(clk1,clk2);
input clk1,clk2;

reg[31:0] PC,IF_ID_IR,IF_ID_NPC;
reg[31:0] ID_EX_IR,ID_EX_NPC,ID_EX_A,ID_EX_B,ID_EX_IMM;
reg[2:0] ID_EX_type,EX_MEM_type,MEM_WB_type;
reg[31:0] EX_MEM_IR,EX_MEM_ALUOUT,EX_MEM_B;
reg EX_MEM_cond;
reg[31:0] MEM_WB_IR,MEM_WB_ALUOUT,MEM_WB_LMD;
reg[31:0] Reg[0:31];
reg[31:0] Mem[0:1023];
parameter ADD=6'b000000,SUB=6'b000001,AND=6'b000010,OR=6'b000011,SLT=6'b000100,MUL=6'b000101,HLT=6'b111111,LW=6'b001000,
          SW=6'b001001,ADDI=6'b001010,SUBI=6'b001011,SLTI=6'b001100,BNEQZ=6'b001101,BEQZ=6'b001110;

parameter RR_ALU=3'b000,RM_ALU=3'b001,LOAD=3'b010,STORE=3'b011,BRANCH=3'b100,HALT=3'b101;

reg HALTED;
reg TAKEN_BRANCH;


always @(posedge clk1)
if(HALTED==0)
begin
    if(((EX_MEM_IR[31:26]==BEQZ)&&(EX_MEM_cond==1))||((EX_MEM_IR[31:26]==BNEQZ)&&(EX_MEM_cond==0)))
    begin
        IF_ID_IR<=#2 Mem[EX_MEM_ALUOUT];
        TAKEN_BRANCH<=#2 1'b1;
        IF_ID_NPC<=#2 EX_MEM_ALUOUT+1;
        PC<=#2 EX_MEM_ALUOUT+1;
    end
    else
    begin
        IF_ID_IR<=#2 Mem[PC];
        IF_ID_NPC<=#2 PC+1;
        PC<=#2 PC+1;
    end
end

always @(posedge clk2)
if(HALTED==0)
begin
    if(IF_ID_IR[25:21]==5'b00000) ID_EX_A<=0;
    else ID_EX_A<=#2 Reg[IF_ID_IR[25:21]];

    if(IF_ID_IR[20:16]==5'b00000) ID_EX_B<=0;
    else ID_EX_B<=#2 Reg[IF_ID_IR[20:16]];

    ID_EX_NPC<=#2 IF_ID_NPC;
    ID_EX_IR<=#2 IF_ID_IR;
    ID_EX_IMM<=#2{{16{IF_ID_IR[15]}},{IF_ID_IR[15:0]}};
    case(IF_ID_IR[31:26])
    ADD,SUB,AND,OR,SLT,MUL: ID_EX_type<=#2 RR_ALU;
    ADDI,SUBI,SLTI:ID_EX_type<= #2 RM_ALU;
    LW:ID_EX_type<= #2 LOAD;
    SW:ID_EX_type<= #2 STORE;
    BNEQZ,BEQZ:ID_EX_type<= #2 BRANCH;
    HLT:ID_EX_type<= #2 HALT;
    default:ID_EX_type<= #2 HALT;
    endcase
end

always @(posedge clk1)
if(HALTED==0)
begin
    EX_MEM_type<= #2 ID_EX_type;
    EX_MEM_IR<= #2 ID_EX_IR;
    TAKEN_BRANCH<= #2 0;

    case(ID_EX_type)
    RR_ALU: begin
        case(ID_EX_IR[31:26])
        ADD:EX_MEM_ALUOUT<= #2 ID_EX_A +ID_EX_B;
        SUB:EX_MEM_ALUOUT<= #2 ID_EX_A -ID_EX_B;
        AND:EX_MEM_ALUOUT<= #2 ID_EX_A &ID_EX_B;
        OR:EX_MEM_ALUOUT<= #2 ID_EX_A |ID_EX_B;
        SLT:EX_MEM_ALUOUT<= #2 ID_EX_A <ID_EX_B;
        MUL:EX_MEM_ALUOUT<= #2 ID_EX_A *ID_EX_B;
        default:EX_MEM_ALUOUT<= #2 32'hxxxxxxxx;
        endcase
    end

    RM_ALU: begin
        case(ID_EX_IR[31:26])
        ADDI:EX_MEM_ALUOUT<= #2 ID_EX_A+ID_EX_IMM;
        SUBI:EX_MEM_ALUOUT<= #2 ID_EX_A-ID_EX_IMM;
        SLTI:EX_MEM_ALUOUT<= #2 ID_EX_A<ID_EX_IMM;
        default:EX_MEM_ALUOUT<= #2 32'hxxxxxxxx;
        endcase
    end
    LOAD,STORE:
    begin
        EX_MEM_ALUOUT<= #2 ID_EX_A+ID_EX_IMM;
        EX_MEM_B<= #2 ID_EX_B;
    end
    BRANCH:
    begin
        EX_MEM_ALUOUT<= #2 ID_EX_NPC+ID_EX_IMM;
        EX_MEM_cond<= #2 (ID_EX_A==0);
    end
    endcase
end

always @(posedge clk2)
if(HALTED==0)
begin
    MEM_WB_type<=#2 EX_MEM_type;
    MEM_WB_IR<= #2 EX_MEM_IR;

    case(EX_MEM_type)
    RR_ALU,RM_ALU:
    MEM_WB_ALUOUT<= #2 EX_MEM_ALUOUT;

    LOAD: MEM_WB_LMD<= #2 Mem[EX_MEM_ALUOUT];
    STORE:if(TAKEN_BRANCH==0)
    Mem[EX_MEM_ALUOUT]<= #2 EX_MEM_B;
    endcase
end

always @(posedge clk1)
begin
    if(TAKEN_BRANCH==0)
    case(MEM_WB_type)
    RR_ALU:Reg[MEM_WB_IR[15:11]]<= MEM_WB_ALUOUT;
    RM_ALU:Reg[MEM_WB_IR[20:16]]<= MEM_WB_ALUOUT;
    LOAD:Reg[MEM_WB_IR[20:16]]<= MEM_WB_LMD;
    HALT:HALTED<= #2 1'b1;
    endcase
end
endmodule

tb3.v
module test3;
reg clk1,clk2;
integer K;
mips32 uut(clk1,clk2);

initial begin
    clk1=0;clk2=0;
    repeat(50)
    begin
        #5 clk1=1;#5 clk1=0;
        #5 clk2=1;#5 clk2=0;
    end
end

initial begin
    for(K=0;K<32;K++)
    uut.Reg[K]=K;

    uut.Mem[0]=32'h280a00c8;
    uut.Mem[1]=32'h28020001;
    uut.Mem[2]=32'h0e94a000;
    uut.Mem[3]=32'h21430000;
    uut.Mem[4]=32'h0e94a000;
    uut.Mem[5]=32'h14431000;
    uut.Mem[6]=32'h2c630001;
    uut.Mem[7]=32'h0e94a000;
    uut.Mem[8]=32'h3460fffc;
    uut.Mem[9]=32'h2542fffe;
    uut.Mem[10]=32'hfc000000;

    uut.Mem[200]=7;
    uut.HALTED=0;
    uut.PC=0;
    uut.TAKEN_BRANCH=0;

    #2000
    $display("Mem[200]=%2d,Mem[198]=%6d",uut.Mem[200],uut.Mem[198]);
    

end

initial begin
    $dumpfile("mips.vcd");
    $dumpvars(0,test3);
    $monitor("R2:%4d",uut.Reg[2]);
    #3000 $finish;
end
endmodule

mips.vcd
$date
	Sun Sep 06 15:34:00 2026
$end
$version
	Icarus Verilog
$end
$timescale
	1s
$end
$scope module test3 $end
$var reg 1 ! clk1 $end
$var reg 1 " clk2 $end
$var integer 32 # K [31:0] $end
$scope module uut $end
$var wire 1 ! clk1 $end
$var wire 1 " clk2 $end
$var reg 32 $ EX_MEM_ALUOUT [31:0] $end
$var reg 32 % EX_MEM_B [31:0] $end
$var reg 32 & EX_MEM_IR [31:0] $end
$var reg 1 ' EX_MEM_cond $end
$var reg 3 ( EX_MEM_type [2:0] $end
$var reg 1 ) HALTED $end
$var reg 32 * ID_EX_A [31:0] $end
$var reg 32 + ID_EX_B [31:0] $end
$var reg 32 , ID_EX_IMM [31:0] $end
$var reg 32 - ID_EX_IR [31:0] $end
$var reg 32 . ID_EX_NPC [31:0] $end
$var reg 3 / ID_EX_type [2:0] $end
$var reg 32 0 IF_ID_IR [31:0] $end
$var reg 32 1 IF_ID_NPC [31:0] $end
$var reg 32 2 MEM_WB_ALUOUT [31:0] $end
$var reg 32 3 MEM_WB_IR [31:0] $end
$var reg 32 4 MEM_WB_LMD [31:0] $end
$var reg 3 5 MEM_WB_type [2:0] $end
$var reg 32 6 PC [31:0] $end
$var reg 1 7 TAKEN_BRANCH $end
$upscope $end
$upscope $end
$enddefinitions $end
#0
$dumpvars
07
b0 6
bx 5
bx 4
bx 3
bx 2
bx 1
bx 0
bx /
bx .
bx -
bx ,
bx +
bx *
0)
bx (
x'
bx &
bx %
bx $
b100000 #
0"
0!
$end
#5
1!
#7
b1 6
b1 1
b101000000010100000000011001000 0
#10
0!
#15
b0 *
1"
#17
b1 /
b11001000 ,
b101000000010100000000011001000 -
b1 .
b1010 +
#20
0"
#25
1!
#27
b11001000 $
b101000000010100000000011001000 &
b1 (
b10 6
b10 1
b101000000000100000000000000001 0
#30
0!
#35
1"
#37
b11001000 2
b101000000010100000000011001000 3
b1 5
b1 ,
b101000000000100000000000000001 -
b10 .
b10 +
#40
0"
#45
1!
#47
b11 6
b11 1
b1110100101001010000000000000 0
b1 $
b101000000000100000000000000001 &
#50
0!
#55
1"
#57
b0 /
b11111111111111111010000000000000 ,
b1110100101001010000000000000 -
b11 .
b10100 +
b10100 *
b1 2
b101000000000100000000000000001 3
#60
0"
#65
1!
#67
b10100 $
b1110100101001010000000000000 &
b0 (
b100 6
b100 1
b100001010000110000000000000000 0
#70
0!
#75
1"
#77
b10100 2
b1110100101001010000000000000 3
b0 5
b10 /
b0 ,
b100001010000110000000000000000 -
b100 .
b11 +
b11001000 *
#80
0"
#85
1!
#87
b101 6
b101 1
b1110100101001010000000000000 0
b11 %
b11001000 $
b100001010000110000000000000000 &
b10 (
#90
0!
#95
1"
#97
b0 /
b11111111111111111010000000000000 ,
b1110100101001010000000000000 -
b101 .
b10100 +
b10100 *
b111 4
b100001010000110000000000000000 3
b10 5
#100
0"
#105
1!
#107
b10100 $
b1110100101001010000000000000 &
b0 (
b110 6
b110 1
b10100010000110001000000000000 0
#110
0!
#115
1"
#117
b1110100101001010000000000000 3
b0 5
b1000000000000 ,
b10100010000110001000000000000 -
b110 .
b111 +
b1 *
#120
0"
#125
1!
#127
b111 6
b111 1
b101100011000110000000000000001 0
b111 $
b10100010000110001000000000000 &
#130
0!
#135
1"
#137
b1 /
b1 ,
b101100011000110000000000000001 -
b111 .
b111 *
b111 2
b10100010000110001000000000000 3
#140
0"
#145
1!
#147
b110 $
b101100011000110000000000000001 &
b1 (
b1000 6
b1000 1
b1110100101001010000000000000 0
#150
0!
#155
1"
#157
b110 2
b101100011000110000000000000001 3
b1 5
b0 /
b11111111111111111010000000000000 ,
b1110100101001010000000000000 -
b1000 .
b10100 +
b10100 *
#160
0"
#165
1!
#167
b1001 6
b1001 1
b110100011000001111111111111100 0
b10100 $
b1110100101001010000000000000 &
b0 (
#170
0!
#175
b0 +
1"
#177
b100 /
b11111111111111111111111111111100 ,
b110100011000001111111111111100 -
b1001 .
b110 *
b10100 2
b1110100101001010000000000000 3
b0 5
#180
0"
#185
1!
#187
0'
b101 $
b110100011000001111111111111100 &
b100 (
b1010 6
b1010 1
b100101010000101111111111111110 0
#190
0!
#195
1"
#197
b110100011000001111111111111100 3
b100 5
b11 /
b11111111111111111111111111111110 ,
b100101010000101111111111111110 -
b1010 .
b111 +
b11001000 *
#200
0"
#205
1!
#207
b110 6
b110 1
17
b10100010000110001000000000000 0
b111 %
b11000110 $
b100101010000101111111111111110 &
b11 (
#210
0!
#215
1"
#217
b0 /
b1000000000000 ,
b10100010000110001000000000000 -
b110 .
b110 +
b111 *
b100101010000101111111111111110 3
b11 5
#220
0"
#225
1!
#227
b101010 $
07
b10100010000110001000000000000 &
b0 (
b111 6
b111 1
b101100011000110000000000000001 0
#230
0!
#235
1"
#237
b101010 2
b10100010000110001000000000000 3
b0 5
b1 /
b1 ,
b101100011000110000000000000001 -
b111 .
b110 *
#240
0"
#245
1!
#247
b1000 6
b1000 1
b1110100101001010000000000000 0
b101 $
b101100011000110000000000000001 &
b1 (
#250
0!
#255
1"
#257
b0 /
b11111111111111111010000000000000 ,
b1110100101001010000000000000 -
b1000 .
b10100 +
b10100 *
b101 2
b101100011000110000000000000001 3
b1 5
#260
0"
#265
1!
#267
b10100 $
b1110100101001010000000000000 &
b0 (
b1001 6
b1001 1
b110100011000001111111111111100 0
#270
0!
#275
b0 +
1"
#277
b10100 2
b1110100101001010000000000000 3
b0 5
b100 /
b11111111111111111111111111111100 ,
b110100011000001111111111111100 -
b1001 .
b101 *
#280
0"
#285
1!
#287
b1010 6
b1010 1
b100101010000101111111111111110 0
b101 $
b110100011000001111111111111100 &
b100 (
#290
0!
#295
1"
#297
b11 /
b11111111111111111111111111111110 ,
b100101010000101111111111111110 -
b1010 .
b101010 +
b11001000 *
b110100011000001111111111111100 3
b100 5
#300
0"
#305
1!
#307
b101010 %
b11000110 $
b100101010000101111111111111110 &
b11 (
b110 6
b110 1
07
b10100010000110001000000000000 0
#310
0!
#315
1"
#317
b100101010000101111111111111110 3
b11 5
b0 /
b1000000000000 ,
b10100010000110001000000000000 -
b110 .
b101 +
b101010 *
#320
0"
#325
1!
#327
b111 6
b111 1
b101100011000110000000000000001 0
b11010010 $
b10100010000110001000000000000 &
b0 (
#330
0!
#335
1"
#337
b1 /
b1 ,
b101100011000110000000000000001 -
b111 .
b101 *
b11010010 2
b10100010000110001000000000000 3
b0 5
#340
0"
#345
1!
#347
b100 $
b101100011000110000000000000001 &
b1 (
b1000 6
b1000 1
b1110100101001010000000000000 0
#350
0!
#355
1"
#357
b100 2
b101100011000110000000000000001 3
b1 5
b0 /
b11111111111111111010000000000000 ,
b1110100101001010000000000000 -
b1000 .
b10100 +
b10100 *
#360
0"
#365
1!
#367
b1001 6
b1001 1
b110100011000001111111111111100 0
b10100 $
b1110100101001010000000000000 &
b0 (
#370
0!
#375
b0 +
1"
#377
b100 /
b11111111111111111111111111111100 ,
b110100011000001111111111111100 -
b1001 .
b100 *
b10100 2
b1110100101001010000000000000 3
b0 5
#380
0"
#385
1!
#387
b101 $
b110100011000001111111111111100 &
b100 (
b1010 6
b1010 1
b100101010000101111111111111110 0
#390
0!
#395
1"
#397
b110100011000001111111111111100 3
b100 5
b11 /
b11111111111111111111111111111110 ,
b100101010000101111111111111110 -
b1010 .
b11010010 +
b11001000 *
#400
0"
#405
1!
#407
b110 6
b110 1
17
b10100010000110001000000000000 0
b11010010 %
b11000110 $
b100101010000101111111111111110 &
b11 (
#410
0!
#415
1"
#417
b0 /
b1000000000000 ,
b10100010000110001000000000000 -
b110 .
b100 +
b11010010 *
b100101010000101111111111111110 3
b11 5
#420
0"
#425
1!
#427
b1101001000 $
07
b10100010000110001000000000000 &
b0 (
b111 6
b111 1
b101100011000110000000000000001 0
#430
0!
#435
1"
#437
b1101001000 2
b10100010000110001000000000000 3
b0 5
b1 /
b1 ,
b101100011000110000000000000001 -
b111 .
b100 *
#440
0"
#445
1!
#447
b1000 6
b1000 1
b1110100101001010000000000000 0
b11 $
b101100011000110000000000000001 &
b1 (
#450
0!
#455
1"
#457
b0 /
b11111111111111111010000000000000 ,
b1110100101001010000000000000 -
b1000 .
b10100 +
b10100 *
b11 2
b101100011000110000000000000001 3
b1 5
#460
0"
#465
1!
#467
b10100 $
b1110100101001010000000000000 &
b0 (
b1001 6
b1001 1
b110100011000001111111111111100 0
#470
0!
#475
b0 +
1"
#477
b10100 2
b1110100101001010000000000000 3
b0 5
b100 /
b11111111111111111111111111111100 ,
b110100011000001111111111111100 -
b1001 .
b11 *
#480
0"
#485
1!
#487
b1010 6
b1010 1
b100101010000101111111111111110 0
b101 $
b110100011000001111111111111100 &
b100 (
#490
0!
#495
1"
#497
b11 /
b11111111111111111111111111111110 ,
b100101010000101111111111111110 -
b1010 .
b1101001000 +
b11001000 *
b110100011000001111111111111100 3
b100 5
#500
0"
#505
1!
#507
b1101001000 %
b11000110 $
b100101010000101111111111111110 &
b11 (
b110 6
b110 1
07
b10100010000110001000000000000 0
#510
0!
#515
1"
#517
b100101010000101111111111111110 3
b11 5
b0 /
b1000000000000 ,
b10100010000110001000000000000 -
b110 .
b11 +
b1101001000 *
#520
0"
#525
1!
#527
b111 6
b111 1
b101100011000110000000000000001 0
b100111011000 $
b10100010000110001000000000000 &
b0 (
#530
0!
#535
1"
#537
b1 /
b1 ,
b101100011000110000000000000001 -
b111 .
b11 *
b100111011000 2
b10100010000110001000000000000 3
b0 5
#540
0"
#545
1!
#547
b10 $
b101100011000110000000000000001 &
b1 (
b1000 6
b1000 1
b1110100101001010000000000000 0
#550
0!
#555
1"
#557
b10 2
b101100011000110000000000000001 3
b1 5
b0 /
b11111111111111111010000000000000 ,
b1110100101001010000000000000 -
b1000 .
b10100 +
b10100 *
#560
0"
#565
1!
#567
b1001 6
b1001 1
b110100011000001111111111111100 0
b10100 $
b1110100101001010000000000000 &
b0 (
#570
0!
#575
b0 +
1"
#577
b100 /
b11111111111111111111111111111100 ,
b110100011000001111111111111100 -
b1001 .
b10 *
b10100 2
b1110100101001010000000000000 3
b0 5
#580
0"
#585
1!
#587
b101 $
b110100011000001111111111111100 &
b100 (
b1010 6
b1010 1
b100101010000101111111111111110 0
#590
0!
#595
1"
#597
b110100011000001111111111111100 3
b100 5
b11 /
b11111111111111111111111111111110 ,
b100101010000101111111111111110 -
b1010 .
b100111011000 +
b11001000 *
#600
0"
#605
1!
#607
b110 6
b110 1
17
b10100010000110001000000000000 0
b100111011000 %
b11000110 $
b100101010000101111111111111110 &
b11 (
#610
0!
#615
1"
#617
b0 /
b1000000000000 ,
b10100010000110001000000000000 -
b110 .
b10 +
b100111011000 *
b100101010000101111111111111110 3
b11 5
#620
0"
#625
1!
#627
b1001110110000 $
07
b10100010000110001000000000000 &
b0 (
b111 6
b111 1
b101100011000110000000000000001 0
#630
0!
#635
1"
#637
b1001110110000 2
b10100010000110001000000000000 3
b0 5
b1 /
b1 ,
b101100011000110000000000000001 -
b111 .
b10 *
#640
0"
#645
1!
#647
b1000 6
b1000 1
b1110100101001010000000000000 0
b1 $
b101100011000110000000000000001 &
b1 (
#650
0!
#655
1"
#657
b0 /
b11111111111111111010000000000000 ,
b1110100101001010000000000000 -
b1000 .
b10100 +
b10100 *
b1 2
b101100011000110000000000000001 3
b1 5
#660
0"
#665
1!
#667
b10100 $
b1110100101001010000000000000 &
b0 (
b1001 6
b1001 1
b110100011000001111111111111100 0
#670
0!
#675
b0 +
1"
#677
b10100 2
b1110100101001010000000000000 3
b0 5
b100 /
b11111111111111111111111111111100 ,
b110100011000001111111111111100 -
b1001 .
b1 *
#680
0"
#685
1!
#687
b1010 6
b1010 1
b100101010000101111111111111110 0
b101 $
b110100011000001111111111111100 &
b100 (
#690
0!
#695
1"
#697
b11 /
b11111111111111111111111111111110 ,
b100101010000101111111111111110 -
b1010 .
b1001110110000 +
b11001000 *
b110100011000001111111111111100 3
b100 5
#700
0"
#705
1!
#707
b1001110110000 %
b11000110 $
b100101010000101111111111111110 &
b11 (
b110 6
b110 1
07
b10100010000110001000000000000 0
#710
0!
#715
1"
#717
b100101010000101111111111111110 3
b11 5
b0 /
b1000000000000 ,
b10100010000110001000000000000 -
b110 .
b1 +
b1001110110000 *
#720
0"
#725
1!
#727
b111 6
b111 1
b101100011000110000000000000001 0
b1001110110000 $
b10100010000110001000000000000 &
b0 (
#730
0!
#735
1"
#737
b1 /
b1 ,
b101100011000110000000000000001 -
b111 .
b1 *
b1001110110000 2
b10100010000110001000000000000 3
b0 5
#740
0"
#745
1!
#747
b0 $
b101100011000110000000000000001 &
b1 (
b1000 6
b1000 1
b1110100101001010000000000000 0
#750
0!
#755
1"
#757
b0 2
b101100011000110000000000000001 3
b1 5
b0 /
b11111111111111111010000000000000 ,
b1110100101001010000000000000 -
b1000 .
b10100 +
b10100 *
#760
0"
#765
1!
#767
b1001 6
b1001 1
b110100011000001111111111111100 0
b10100 $
b1110100101001010000000000000 &
b0 (
#770
0!
#775
b0 +
1"
#777
b100 /
b11111111111111111111111111111100 ,
b110100011000001111111111111100 -
b1001 .
b0 *
b10100 2
b1110100101001010000000000000 3
b0 5
#780
0"
#785
1!
#787
1'
b101 $
b110100011000001111111111111100 &
b100 (
b1010 6
b1010 1
b100101010000101111111111111110 0
#790
0!
#795
1"
#797
b110100011000001111111111111100 3
b100 5
b11 /
b11111111111111111111111111111110 ,
b100101010000101111111111111110 -
b1010 .
b1001110110000 +
b11001000 *
#800
0"
#805
1!
#807
b1011 6
b1011 1
b11111100000000000000000000000000 0
b11000110 $
b100101010000101111111111111110 &
b11 (
#810
0!
#815
b0 +
b0 *
1"
#817
b101 /
b0 ,
b11111100000000000000000000000000 -
b1011 .
b100101010000101111111111111110 3
b11 5
#820
0"
#825
1!
#827
b11111100000000000000000000000000 &
b101 (
b1100 6
b1100 1
bx 0
#830
0!
#835
1"
#837
b11111100000000000000000000000000 3
b101 5
bx ,
bx -
b1100 .
bx +
bx *
#840
0"
#845
1!
#847
b1101 6
b1101 1
bx &
1)
